mapkick/static/__init__.py
mapkick_static-0.1.0.dist-info/LICENSE.txt
mapkick_static-0.1.0.dist-info/METADATA
mapkick_static-0.1.0.dist-info/WHEEL
mapkick_static-0.1.0.dist-info/top_level.txt
mapkick_static-0.1.0.dist-info/RECORD
