Metadata-Version: 2.1
Name: mapkick-static
Version: 0.1.0
Summary: Create beautiful static maps with one line of Python
Home-page: https://github.com/ankane/mapkick-static.py
Author: Andrew Kane
Author-email: andrew@ankane.org
License: MIT
Requires-Python: >=3.8
License-File: LICENSE.txt
